ElectricCircuitSim/__init__.py
ElectricCircuitSim/py.typed
ElectricCircuitSim/analyze/__init__.py
ElectricCircuitSim/analyze/__init__.pyi
ElectricCircuitSim/analyze/analyzer.py
ElectricCircuitSim/analyze/analyzer.pyi
ElectricCircuitSim/core/__init__.py
ElectricCircuitSim/core/__init__.pyi
ElectricCircuitSim/core/_electric_sim.pyi
ElectricCircuitSim-0.0.2.dist-info/LICENSE.txt
ElectricCircuitSim-0.0.2.dist-info/METADATA
ElectricCircuitSim-0.0.2.dist-info/WHEEL
ElectricCircuitSim-0.0.2.dist-info/top_level.txt
ElectricCircuitSim-0.0.2.dist-info/RECORD
