Metadata-Version: 2.2
Name: ElectricCircuitSim
Version: 0.0.2
Summary: A powerful Python package for simulating electrical circuits and generators.
Author-email: Maciej Krakowiak <maciej.krakowiak17@gmail.com>
License: MIT
Keywords: simulation,electrical circuits,generators,RL circuit,sinusoidal,square wave
Classifier: Development Status :: 4 - Beta
Classifier: Intended Audience :: Developers
Classifier: Intended Audience :: Education
Classifier: Intended Audience :: Science/Research
Classifier: License :: OSI Approved :: MIT License
Classifier: Programming Language :: Python :: 3.11
Classifier: Topic :: Scientific/Engineering :: Physics
Classifier: Topic :: Software Development :: Libraries :: Python Modules
Requires-Python: >=3.11
License-File: LICENSE.txt
Requires-Dist: matplotlib>=3.10.0
